{
  "attackCount": [
    [
      0,
      0
    ],
    [
      0,
      0
    ],
    [
      0,
      0
    ],
    [
      0,
      0
    ],
    [
      0,
      0
    ],
    [
      0,
      0
    ],
    [
      0,
      0
    ],
    [
      0,
      0
    ],
    [
      0,
      0
    ],
    [
      0,
      0
    ],
    [
      0,
      0
    ],
    [
      0,
      0
    ],
    [
      0,
      0
    ],
    [
      0,
      0
    ],
    [
      0,
      0
    ],
    [
      0,
      0
    ],
    [
      0,
      0
    ],
    [
      0,
      0
    ],
    [
      0,
      0
    ],
    [
      0,
      0
    ],
    [
      0,
      0
    ],
    [
      0,
      0
    ],
    [
      0,
      0
    ],
    [
      0,
      0
    ],
    [
      0,
      0
    ],
    [
      0,
      0
    ],
    [
      0,
      0
    ],
    [
      0,
      0
    ],
    [
      0,
      0
    ],
    [
      0,
      0
    ],
    [
      0,
      0
    ],
    [
      0,
      0
    ],
    [
      0,
      0
    ],
    [
      0,
      0
    ],
    [
      0,
      0
    ],
    [
      0,
      0
    ],
    [
      0,
      0
    ],
    [
      0,
      0
    ],
    [
      0,
      0
    ],
    [
      0,
      0
    ]
  ],
  "id": 0,
  "name": "TURANIAN_MACER",
  "maxPossibleMoving": 2,
  "price": 450,
  "healthPoint": 3,
  "minRange": -1,
  "maxRange": -1,
  "assaultPower": 10,
  "originalAssaultPower": 10,
  "assaultType": "MELEE",
  "buffs": [],
  "castedBuffs": [],
  "castedItems": [],
  "manaPoint": 2,
  "ableToAttack": false,
  "ableToMove": false,
  "ableToResist": false,
  "ableToCounter": false,
  "cardHolder": 0,
  "isHoly": 0
}